datasets/__init__.py
datasets/fusillo-20091002-B.npy
datasets/fusillo-20091002-B.txt
datasets/fusillo-20091002-fgrad.npy
datasets/fusillo-20091002-fgrad.txt
datasets/fusillo-20091002-h.DSC
datasets/fusillo-20091002-h.DTA
datasets/fusillo-20091002-h.npy
datasets/fusillo-20091002-h.txt
datasets/fusillo-20091002-proj.DSC
datasets/fusillo-20091002-proj.DTA
datasets/fusillo-20091002-proj.npy
datasets/fusillo-20091002-proj.txt
datasets/phalanx-20220203-B.npy
datasets/phalanx-20220203-B.txt
datasets/phalanx-20220203-fgrad.npy
datasets/phalanx-20220203-fgrad.txt
datasets/phalanx-20220203-h.DSC
datasets/phalanx-20220203-h.DTA
datasets/phalanx-20220203-h.npy
datasets/phalanx-20220203-h.txt
datasets/phalanx-20220203-proj.DSC
datasets/phalanx-20220203-proj.DTA
datasets/phalanx-20220203-proj.npy
datasets/phalanx-20220203-proj.txt
pyepri/__init__.py
pyepri/apodization.py
pyepri/backends.py
pyepri/checks.py
pyepri/displayers.py
pyepri/io.py
pyepri/monosrc.py
pyepri/multisrc.py
pyepri/optimization.py
pyepri/processing.py
pyepri/spectralspatial.py
pyepri/utils.py
pyepri/datasets/__init__.py
pyepri/datasets/bacteria-inkjet-20100709-h.pkl
pyepri/datasets/bacteria-inkjet-20100709-proj.pkl
pyepri/datasets/beads-phantom-20080313-h.pkl
pyepri/datasets/beads-phantom-20080313-proj.pkl
pyepri/datasets/beads-thintubes-20081017-h.pkl
pyepri/datasets/beads-thintubes-20081017-proj.pkl
pyepri/datasets/cnrs-inkjet-20110614-h.pkl
pyepri/datasets/cnrs-inkjet-20110614-proj.pkl
pyepri/datasets/dpph-logo-20080402-h.pkl
pyepri/datasets/dpph-logo-20080402-proj.pkl
pyepri/datasets/fusillo-20091002-B.npy
pyepri/datasets/fusillo-20091002-B.txt
pyepri/datasets/fusillo-20091002-fgrad.npy
pyepri/datasets/fusillo-20091002-fgrad.txt
pyepri/datasets/fusillo-20091002-h.DSC
pyepri/datasets/fusillo-20091002-h.DTA
pyepri/datasets/fusillo-20091002-h.npy
pyepri/datasets/fusillo-20091002-h.pkl
pyepri/datasets/fusillo-20091002-h.txt
pyepri/datasets/fusillo-20091002-proj.DSC
pyepri/datasets/fusillo-20091002-proj.DTA
pyepri-1.1.1.dist-info/licenses/LICENSE
pyepri-1.1.1.dist-info/METADATA
pyepri-1.1.1.dist-info/WHEEL
pyepri-1.1.1.dist-info/top_level.txt
pyepri-1.1.1.dist-info/RECORD
