Metadata-Version: 2.4
Name: pyepri
Version: 1.1.1
Summary: A CPU & GPU compatible Python package for Electron Paramagnetic Resonance Imaging
Author-email: Rémy Abergel <Remy.Abergel@math.cnrs.fr>
License-Expression: MIT
Project-URL: Homepage, https://github.com/remy-abergel/pyepri
Project-URL: Issues, https://github.com/remy-abergel/pyepri/issues
Classifier: Programming Language :: Python :: 3
Classifier: Operating System :: OS Independent
Requires-Python: >=3.8
License-File: LICENSE
Requires-Dist: numpy>=2.2.4
Requires-Dist: scipy
Requires-Dist: matplotlib
Requires-Dist: pyvista>=0.44.0
Requires-Dist: finufft>=2.4.0
Requires-Dist: jupyter
Requires-Dist: psutil
Provides-Extra: cupy-cuda12x
Requires-Dist: cupy-cuda12x; extra == "cupy-cuda12x"
Requires-Dist: cufinufft>=2.4.0; extra == "cupy-cuda12x"
Provides-Extra: cupy-cuda11x
Requires-Dist: cupy-cuda11x; extra == "cupy-cuda11x"
Requires-Dist: cufinufft; extra == "cupy-cuda11x"
Provides-Extra: torch-cpu
Requires-Dist: torch>=2.5.1; extra == "torch-cpu"
Requires-Dist: torchinterp1d; extra == "torch-cpu"
Provides-Extra: torch-cuda
Requires-Dist: torch>=2.5.1; extra == "torch-cuda"
Requires-Dist: torchinterp1d; extra == "torch-cuda"
Requires-Dist: cufinufft>=2.4.0; extra == "torch-cuda"
Provides-Extra: dev
Requires-Dist: pytest; extra == "dev"
Requires-Dist: pytest-cov; extra == "dev"
Provides-Extra: doc
Requires-Dist: myst_parser; extra == "doc"
Requires-Dist: sphinx-rtd-theme>=0.4.2; extra == "doc"
Requires-Dist: sphinx-autoapi; extra == "doc"
Requires-Dist: sphinx-gallery; extra == "doc"
Requires-Dist: sphinx-tabs; extra == "doc"
Requires-Dist: sphinx-design; extra == "doc"
Requires-Dist: pyvista[all,trame]; extra == "doc"
Requires-Dist: memory_profiler; extra == "doc"
Requires-Dist: ipywidgets; extra == "doc"
Requires-Dist: ipyvtklink; extra == "doc"
Requires-Dist: sphinxcontrib-bibtex; extra == "doc"
Requires-Dist: sphinxcontrib-video; extra == "doc"
Provides-Extra: jupyter
Requires-Dist: trame; extra == "jupyter"
Requires-Dist: trame-vtk; extra == "jupyter"
Requires-Dist: trame-vuetify; extra == "jupyter"
Provides-Extra: cupy-rocm-5-0
Requires-Dist: cupy-rocm-5-0; extra == "cupy-rocm-5-0"
Requires-Dist: cufinufft; extra == "cupy-rocm-5-0"
Provides-Extra: cupy-rocm-4-3
Requires-Dist: cupy-rocm-4-3; extra == "cupy-rocm-4-3"
Requires-Dist: cutensor; extra == "cupy-rocm-4-3"
Requires-Dist: cufinufft; extra == "cupy-rocm-4-3"
Dynamic: license-file
